eic_codebase_analysis/__init__.py
eic_codebase_analysis/detailed_code_content_extractor/__init__.py
eic_codebase_analysis/detailed_code_content_extractor/core.py
eic_codebase_analysis/detailed_code_content_extractor/main.py
eic_codebase_analysis/detailed_code_content_extractor/utils.py
eic_codebase_analysis/hierarchical_project_metadata_generator/__init__.py
eic_codebase_analysis/hierarchical_project_metadata_generator/gemini_utils.py
eic_codebase_analysis/hierarchical_project_metadata_generator/generator.py
eic_codebase_analysis/hierarchical_project_metadata_generator/main.py
eic_codebase_analysis/hierarchical_project_metadata_generator/utils.py
eic_codebase_analysis/repository_file_metadata_generator/__init__.py
eic_codebase_analysis/repository_file_metadata_generator/gemini_utils.py
eic_codebase_analysis/repository_file_metadata_generator/generator.py
eic_codebase_analysis/repository_file_metadata_generator/main.py
eic_codebase_analysis/repository_file_metadata_generator/utils.py
eic_codebase_analysis/repository_structure_extractor/__init__.py
eic_codebase_analysis/repository_structure_extractor/generator.py
eic_codebase_analysis/repository_structure_extractor/main.py
eic_codebase_analysis/repository_structure_extractor/utils.py
eic_codebase_analysis-0.1.1.dist-info/licenses/LICENSE
eic_consistency_engine/cli.py
eic_consistency_engine/core/__init__.py
eic_consistency_engine/core/code_structure.py
eic_consistency_engine/core/gemini_client.py
eic_consistency_engine/core/language_loader.py
eic_consistency_engine/core/language_models.py
eic_consistency_engine/core/linter_integration.py
eic_consistency_engine/core/reference_init.py
eic_consistency_engine/core/repo_analysis.py
eic_consistency_engine/lang/__init__.py
eic_consistency_engine/lang/angular.py
eic_consistency_engine/lang/dotnet.py
eic_consistency_engine/lang/go.py
eic_consistency_engine/lang/java.py
eic_consistency_engine/lang/nodejs.py
eic_consistency_engine/lang/powershell.py
eic_consistency_engine/lang/python.py
eic_consistency_engine/lang/react.py
eic_codebase_analysis-0.1.1.dist-info/METADATA
eic_codebase_analysis-0.1.1.dist-info/WHEEL
eic_codebase_analysis-0.1.1.dist-info/top_level.txt
eic_codebase_analysis-0.1.1.dist-info/RECORD
