Metadata-Version: 2.4
Name: eic-codebase-analysis
Version: 0.1.1
Summary: A library for codebase analysis
Author-email: Entinco <info@entinco.com>
Project-URL: Homepage, https://bitbucket.org/entinco/eic-aimodelknowledge-utils
Project-URL: Bug Tracker, https://bitbucket.org/entinco/eic-aimodelknowledge-utils/issues
Classifier: Programming Language :: Python :: 3
Classifier: License :: OSI Approved :: MIT License
Classifier: Operating System :: OS Independent
Requires-Python: >=3.7
License-File: LICENSE
Requires-Dist: google-generativeai
Dynamic: license-file
